hkopenai/hk_transportation_mcp_server/__init__.py
hkopenai/hk_transportation_mcp_server/__main__.py
hkopenai/hk_transportation_mcp_server/app.py
hkopenai/hk_transportation_mcp_server/decorators.py
hkopenai/hk_transportation_mcp_server/tool_bus_kmb.py
hkopenai/hk_transportation_mcp_server/tool_land_custom_wait_time.py
hkopenai/hk_transportation_mcp_server/tool_passenger_traffic.py
hkopenai_hk_transportation_mcp_server-0.2.8.dist-info/licenses/LICENSE
hkopenai_hk_transportation_mcp_server-0.2.8.dist-info/METADATA
hkopenai_hk_transportation_mcp_server-0.2.8.dist-info/WHEEL
hkopenai_hk_transportation_mcp_server-0.2.8.dist-info/entry_points.txt
hkopenai_hk_transportation_mcp_server-0.2.8.dist-info/top_level.txt
hkopenai_hk_transportation_mcp_server-0.2.8.dist-info/RECORD
